absql/__init__.py
absql/files/__init__.py
absql/files/loader.py
absql/files/parsers.py
absql/functions/__init__.py
absql/functions/db.py
absql/functions/env.py
absql/functions/time.py
absql/render/__init__.py
absql/text/__init__.py
absql/utils/__init__.py
tests/__init__.py
tests/test_copy.py
tests/test_funcs_db.py
tests/test_funcs_env.py
tests/test_funcs_time.py
tests/test_loader.py
tests/test_parse_file.py
tests/test_partial_kwargs.py
tests/test_render.py
tests/test_render_file.py
tests/test_render_file_return_dict.py
tests/test_render_text.py
tests/test_set.py
tests/test_text.py
tests/test_utils.py
ABSQL-0.6.1.dist-info/LICENSE
ABSQL-0.6.1.dist-info/METADATA
ABSQL-0.6.1.dist-info/WHEEL
ABSQL-0.6.1.dist-info/top_level.txt
ABSQL-0.6.1.dist-info/RECORD
