Metadata-Version: 2.1
Name: ABSQL
Version: 0.6.1
Summary: A rendering engine for templated SQL
Home-page: https://github.com/pipeline-tools/ABSQL
Author: Chris Cardillo
Author-email: cfcardillo23@gmail.com
Classifier: Programming Language :: Python :: 3
Classifier: License :: OSI Approved :: MIT License
Classifier: Operating System :: OS Independent
Requires-Python: >=3.6
License-File: LICENSE
Requires-Dist: colorama
Requires-Dist: flatdict
Requires-Dist: Jinja2
Requires-Dist: jupytext
Requires-Dist: pendulum
Requires-Dist: PyYaml
Requires-Dist: SQLAlchemy
Requires-Dist: sql-metadata
